brainglobe_napari_io/__init__.py
brainglobe_napari_io/napari.yaml
brainglobe_napari_io/utils.py
brainglobe_napari_io/brainmapper/__init__.py
brainglobe_napari_io/brainmapper/brainmapper_reader_dir.py
brainglobe_napari_io/brainreg/__init__.py
brainglobe_napari_io/brainreg/reader_dir.py
brainglobe_napari_io/brainreg/reader_dir_atlas_space.py
brainglobe_napari_io/brainreg/reader_dir_sample_space.py
brainglobe_napari_io/cellfinder/__init__.py
brainglobe_napari_io/cellfinder/reader_xml.py
brainglobe_napari_io/cellfinder/utils.py
brainglobe_napari_io/cellfinder/writer_xml.py
brainglobe_napari_io-0.4.0.dist-info/licenses/LICENSE
brainglobe_napari_io-0.4.0.dist-info/METADATA
brainglobe_napari_io-0.4.0.dist-info/WHEEL
brainglobe_napari_io-0.4.0.dist-info/entry_points.txt
brainglobe_napari_io-0.4.0.dist-info/top_level.txt
brainglobe_napari_io-0.4.0.dist-info/RECORD
