Metadata-Version: 2.4
Name: brainglobe-napari-io
Version: 0.4.0
Summary: Read and write files from the BrainGlobe computational neuroanatomy suite into napari
Author-email: Adam Tyson <hello@brainglobe.info>
License: BSD-3-Clause
Project-URL: Homepage, https://brainglobe.info
Project-URL: Source Code, https://github.com/brainglobe/brainglobe-napari-io
Project-URL: Bug Tracker, https://github.com/brainglobe/brainglobe-napari-io/issues
Project-URL: Documentation, https://docs.brainglobe.info
Project-URL: User Support, https://forum.image.sc/tag/brainglobe
Project-URL: Twitter, https://twitter.com/brain_globe
Classifier: Development Status :: 4 - Beta
Classifier: Framework :: napari
Classifier: Intended Audience :: Science/Research
Classifier: Operating System :: OS Independent
Classifier: Programming Language :: Python
Classifier: Programming Language :: Python :: 3
Classifier: Programming Language :: Python :: 3.11
Classifier: Programming Language :: Python :: 3.12
Classifier: Programming Language :: Python :: 3.13
Classifier: Topic :: Scientific/Engineering :: Image Recognition
Requires-Python: >=3.11
License-File: LICENSE
Requires-Dist: brainglobe-atlasapi>=2.0.1
Requires-Dist: brainglobe-space>=1.0.0
Requires-Dist: brainglobe-utils>=0.4.2
Requires-Dist: napari>=0.6.1
Requires-Dist: tifffile>=2020.8.13
Requires-Dist: numpy
Requires-Dist: pandas
Provides-Extra: dev
Requires-Dist: pytest; extra == "dev"
Requires-Dist: pytest-cov; extra == "dev"
Requires-Dist: pytest-mock; extra == "dev"
Requires-Dist: pytest-qt; extra == "dev"
Requires-Dist: coverage; extra == "dev"
Requires-Dist: tox; extra == "dev"
Requires-Dist: black; extra == "dev"
Requires-Dist: mypy; extra == "dev"
Requires-Dist: pre-commit; extra == "dev"
Requires-Dist: ruff; extra == "dev"
Requires-Dist: setuptools_scm; extra == "dev"
Requires-Dist: pyqt5; extra == "dev"
Dynamic: license-file
